{
  "$schema": "https://frank1o3.github.io/ModForge-CLI/schemas/policy.schema.json",
  "sodium": {
    "conflicts": [
      "vulkanmod",
      "vulkanmod-extra"
    ],
    "sub_mods": [
      "sodium-extra",
      "reeses-sodium-options",
      "immediatelyfast"
    ]
  },
  "podium": {
    "sub_mods": [
      "sodium"
    ],
    "conflicts": [
      "vulkanmod"
    ]
  },
  "vulkanmod": {
    "conflicts": [
      "sodium",
      "sodium-extra",
      "reeses-sodium-options",
      "immediatelyfast"
    ],
    "sub_mods": [
      "vulkanmod-extra"
    ]
  },
  "mod-menu": {
    "sub_mods": [
      "yetanotherconfiglib",
      "cloth-config-api"
    ],
    "conflicts": []
  },
  "fabric-api": {
    "sub_mods": [
      "fabric-language"
    ],
    "conflicts": []
  },
  "3d-skin-layers": {
    "sub_mods": [
      "not-enough-animations",
      "wavey-capes"
    ],
    "conflicts": []
  }
}